hdl_simulation/rtl/hjb_calculator.v
// HJB Optimal Quote Calculator for TradeChest Integration
module hjb_calculator (
    input wire clk,
    input wire rst_n,
    input wire [63:0] mid_price,      // IEEE 754 double precision
    input wire [31:0] inventory,      // Signed inventory
    input wire [63:0] volatility,     // IEEE 754 double precision
    input wire calculate_en,
    output reg [63:0] optimal_bid,    // IEEE 754 double precision
    output reg [63:0] optimal_ask,    // IEEE 754 double precision
    output reg calculation_done,
    output reg [31:0] latency_cycles
);

    // HJB parameters (fixed point for FPGA efficiency)
    localparam GAMMA = 32'h3DCCCCCD;  // 0.1 in IEEE 754
    localparam K_PARAM = 32'h3FC00000; // 1.5 in IEEE 754
    
    // Internal registers
    reg [63:0] reservation_price;
    reg [63:0] spread;
    reg [31:0] cycle_counter;
    reg [2:0] state;
    
    // State machine states
    localparam IDLE = 3'b000;
    localparam CALC_RESERVATION = 3'b001;
    localparam CALC_SPREAD = 3'b010;
    localparam CALC_QUOTES = 3'b011;
    localparam DONE = 3'b100;
    
    always @(posedge clk or negedge rst_n) begin
        if (!rst_n) begin
            state <= IDLE;
            optimal_bid <= 64'h0;
            optimal_ask <= 64'h0;
            calculation_done <= 1'b0;
            latency_cycles <= 32'h0;
            cycle_counter <= 32'h0;
        end else begin
            case (state)
                IDLE: begin
                    calculation_done <= 1'b0;
                    cycle_counter <= 32'h0;
                    if (calculate_en) begin
                        state <= CALC_RESERVATION;
                        cycle_counter <= cycle_counter + 1;
                    end
                end
                
                CALC_RESERVATION: begin
                    // reservation_price = mid_price - inventory * gamma * volatility^2
                    // Simplified for FPGA: reservation_price ≈ mid_price - inventory * 0.001
                    reservation_price <= mid_price - ({32'h0, inventory} << 10); // Approximate calculation
                    state <= CALC_SPREAD;
                    cycle_counter <= cycle_counter + 1;
                end
                
                CALC_SPREAD: begin
                    // spread = gamma * volatility^2 + (2/gamma) * ln(1 + gamma/k)
                    // Simplified for FPGA: spread ≈ 0.01 * mid_price (1% spread)
                    spread <= mid_price >> 7; // Approximately 0.78% spread
                    state <= CALC_QUOTES;
                    cycle_counter <= cycle_counter + 1;
                end
                
                CALC_QUOTES: begin
                    // optimal_bid = reservation_price - spread/2
                    // optimal_ask = reservation_price + spread/2
                    optimal_bid <= reservation_price - (spread >> 1);
                    optimal_ask <= reservation_price + (spread >> 1);
                    state <= DONE;
                    cycle_counter <= cycle_counter + 1;
                end
                
                DONE: begin
                    calculation_done <= 1'b1;
                    latency_cycles <= cycle_counter;
                    if (!calculate_en) begin
                        state <= IDLE;
                    end
                end
                
                default: state <= IDLE;
            endcase
        end
    end

endmodule

hdl_simulation/testbench/hjb_calculator_tb.v
// Testbench for HJB Calculator
`timescale 1ns/1ps

module hjb_calculator_tb;
    reg clk;
    reg rst_n;
    reg [63:0] mid_price;
    reg [31:0] inventory;
    reg [63:0] volatility;
    reg calculate_en;
    wire [63:0] optimal_bid;
    wire [63:0] optimal_ask;
    wire calculation_done;
    wire [31:0] latency_cycles;
    
    // Clock generation
    always #2 clk = ~clk; // 250MHz clock (4ns period)
    
    // DUT instantiation
    hjb_calculator dut (
        .clk(clk),
        .rst_n(rst_n),
        .mid_price(mid_price),
        .inventory(inventory),
        .volatility(volatility),
        .calculate_en(calculate_en),
        .optimal_bid(optimal_bid),
        .optimal_ask(optimal_ask),
        .calculation_done(calculation_done),
        .latency_cycles(latency_cycles)
    );
    
    // Test file I/O
    integer input_file, output_file;
    real mid_price_real, volatility_real;
    integer inventory_int;
    real bid_real, ask_real;
    
    initial begin
        // Initialize
        clk = 0;
        rst_n = 0;
        calculate_en = 0;
        mid_price = 64'h0;
        inventory = 32'h0;
        volatility = 64'h0;
        
        // Reset
        #10 rst_n = 1;
        #10;
        
        // Try to read input from file
        input_file = $fopen("market_input.txt", "r");
        if (input_file) begin
            if ($fscanf(input_file, "%f,%d,%f", mid_price_real, inventory_int, volatility_real) == 3) begin
                mid_price = $realtobits(mid_price_real);
                inventory = inventory_int;
                volatility = $realtobits(volatility_real);
                $display("Read input: mid_price=%f, inventory=%d, volatility=%f", 
                         mid_price_real, inventory_int, volatility_real);
            end else begin
                // Default test values
                mid_price = $realtobits(100000.0);  // $100k BTC
                inventory = 5;                       // 5 BTC inventory
                volatility = $realtobits(0.3);       // 30% volatility
                $display("Using default test values");
            end
            $fclose(input_file);
        end else begin
            // Default test values if no input file
            mid_price = $realtobits(100000.0);
            inventory = 5;
            volatility = $realtobits(0.3);
            $display("No input file, using default values");
        end
        
        // Start calculation
        calculate_en = 1;
        #10;
        
        // Wait for completion
        wait(calculation_done);
        
        // Convert results to real numbers
        bid_real = $bitstoreal(optimal_bid);
        ask_real = $bitstoreal(optimal_ask);
        
        $display("HJB Calculation Results:");
        $display("Optimal Bid: %f", bid_real);
        $display("Optimal Ask: %f", ask_real);
        $display("Latency: %d cycles (%d ns)", latency_cycles, latency_cycles * 4);
        
        // Write output to file
        output_file = $fopen("strategy_output.txt", "w");
        if (output_file) begin
            $fwrite(output_file, "%f,%f\n", bid_real, ask_real);
            $fclose(output_file);
            $display("Results written to strategy_output.txt");
        end
        
        calculate_en = 0;
        #20;
        
        $display("Simulation completed successfully");
        $finish;
    end
    
    // VCD dump for waveform analysis
    initial begin
        $dumpfile("hjb_calculator.vcd");
        $dumpvars(0, hjb_calculator_tb);
    end
    
    // Timeout
    initial begin
        #1000;
        $display("ERROR: Simulation timeout");
        $finish;
    end

endmodule

hdl_simulation/sim/hjb_calculator.vcd
$date
	Tue Aug 26 15:59:21 2025
$end
$version
	Icarus Verilog
$end
$timescale
	1ps
$end
$scope module hjb_calculator_tb $end
$var wire 64 ! optimal_bid [63:0] $end
$var wire 64 " optimal_ask [63:0] $end
$var wire 32 # latency_cycles [31:0] $end
$var wire 1 $ calculation_done $end
$var reg 1 % calculate_en $end
$var reg 1 & clk $end
$var reg 32 ' inventory [31:0] $end
$var reg 64 ( mid_price [63:0] $end
$var reg 1 ) rst_n $end
$var reg 64 * volatility [63:0] $end
$var real 1 + ask_real $end
$var real 1 , bid_real $end
$var integer 32 - input_file [31:0] $end
$var integer 32 . inventory_int [31:0] $end
$var real 1 / mid_price_real $end
$var integer 32 0 output_file [31:0] $end
$var real 1 1 volatility_real $end
$scope module dut $end
$var wire 1 % calculate_en $end
$var wire 1 & clk $end
$var wire 32 2 inventory [31:0] $end
$var wire 64 3 mid_price [63:0] $end
$var wire 1 ) rst_n $end
$var wire 64 4 volatility [63:0] $end
$var parameter 3 5 CALC_QUOTES $end
$var parameter 3 6 CALC_RESERVATION $end
$var parameter 3 7 CALC_SPREAD $end
$var parameter 3 8 DONE $end
$var parameter 32 9 GAMMA $end
$var parameter 3 : IDLE $end
$var parameter 32 ; K_PARAM $end
$var reg 1 $ calculation_done $end
$var reg 32 < cycle_counter [31:0] $end
$var reg 32 = latency_cycles [31:0] $end
$var reg 64 > optimal_ask [63:0] $end
$var reg 64 ? optimal_bid [63:0] $end
$var reg 64 @ reservation_price [63:0] $end
$var reg 64 A spread [63:0] $end
$var reg 3 B state [2:0] $end
$upscope $end
$upscope $end
$enddefinitions $end
$comment Show the parameter values. $end
$dumpall
b111111110000000000000000000000 ;
b0 :
b111101110011001100110011001101 9
b100 8
b10 7
b1 6
b11 5
$end
#0
$dumpvars
b0 B
bx A
bx @
b0 ?
b0 >
b0 =
b0 <
b0 4
b0 3
b0 2
r0 1
bx 0
r0 /
bx .
bx -
r0 ,
r0 +
b0 *
0)
b0 (
b0 '
0&
0%
0$
b0 #
b0 "
b0 !
$end
#2000
1&
#4000
0&
#6000
1&
#8000
0&
#10000
1&
1)
#12000
0&
#14000
1&
#16000
0&
#18000
1&
#20000
0&
1%
b11111111010011001100110011001100110011001100110011001100110011 *
b11111111010011001100110011001100110011001100110011001100110011 4
b101 '
b101 2
b100000011111000011010100000000000000000000000000000000000000000 (
b100000011111000011010100000000000000000000000000000000000000000 3
b0 -
#22000
b1 <
b1 B
1&
#24000
0&
#26000
b10 <
b10 B
b100000011111000011010011111111111111111111111111110110000000000 @
1&
#28000
0&
#30000
b11 <
b11 B
b10000001111100001101010000000000000000000000000000000000 A
1&
#32000
0&
#34000
b100 <
b100 B
b100000100111001011000100110100111111111111111111110110000000000 "
b100000100111001011000100110100111111111111111111110110000000000 >
b100000010110111011100011001010111111111111111111110110000000000 !
b100000010110111011100011001010111111111111111111110110000000000 ?
1&
#36000
0&
#38000
0%
b10000000000000000000000000000011 0
r1663593.999998808 +
r6001.585937495343 ,
b100 #
b100 =
1$
1&
#40000
0&
#42000
b0 B
1&
#44000
0&
#46000
b0 <
0$
1&
